classification_f_20/__init__.py
classification_f_20/run.py
classifiction_f_20-0.0.1.dist-info/LICENSE
classifiction_f_20-0.0.1.dist-info/METADATA
classifiction_f_20-0.0.1.dist-info/WHEEL
classifiction_f_20-0.0.1.dist-info/top_level.txt
classifiction_f_20-0.0.1.dist-info/RECORD
