Metadata-Version: 2.1
Name: classifiction-f-20
Version: 0.0.1
Summary: Used to predict the properties of f_20
Home-page: https://github.com/pypa/sampleproject
Author: karen
Author-email: 962388544@qq.com
License: UNKNOWN
Platform: UNKNOWN
Classifier: Programming Language :: Python :: 2
Classifier: License :: OSI Approved :: MIT License
Classifier: Operating System :: OS Independent
Requires-Python: >=2.6
